snowflake_opendic/catalog.py
snowflake_opendic/cli.py
snowflake_opendic/client.py
snowflake_opendic/model/openapi_models.py
snowflake_opendic/patterns/opendic_patterns.py
snowflake_opendic/pretty_pesponse.py
snowflake_opendic/snow_opendic.py
snowflake_opendic/__init__.py
snowflake_opendic-0.1.23.dist-info/WHEEL
snowflake_opendic-0.1.23.dist-info/entry_points.txt
snowflake_opendic-0.1.23.dist-info/METADATA
snowflake_opendic-0.1.23.dist-info/RECORD
