Metadata-Version: 2.3
Name: snowflake-opendic
Version: 0.1.23
Summary: Add your description here
Author: akongstad, carlbrr
Author-email: akongstad <kongstad@outlook.com>, carlbrr <carl99@live.dk>
Requires-Dist: pandas>=2.2.3
Requires-Dist: pydantic>=2.11.3
Requires-Dist: snowflake-connector-python[pandas]>=3.13.2
Requires-Dist: toml>=0.10.2
Requires-Python: >=3.9
Project-URL: Homepage, https://github.com/msc-open-metadata/snowflake-opendic
